rito/__init__.py
rito/cli.py
rito/get_cli.py
rito/tsv.py
rito/receivers/__init__.py
rito/receivers/slack.py
rito/senders/__init__.py
rito/senders/att.py
rito/senders/file.py
rito/senders/migadu.py
rito/senders/slack.py
rito/senders/slack_file.py
rito/senders/slack_image.py
rito/senders/zulip.py
rito-0.0.8.dist-info/LICENSE
rito-0.0.8.dist-info/METADATA
rito-0.0.8.dist-info/WHEEL
rito-0.0.8.dist-info/entry_points.txt
rito-0.0.8.dist-info/top_level.txt
rito-0.0.8.dist-info/RECORD
