Metadata-Version: 2.1
Name: rito
Version: 0.0.8
Summary: Very simple ways to send notifications
Home-page: https://github.com/NQNStudios/rito
Author: Nat Quayle Nelson
Author-email: natquaylenelson@gmail.com
License: UNKNOWN
Platform: UNKNOWN
Classifier: Programming Language :: Python :: 3
Classifier: License :: OSI Approved :: MIT License
Classifier: Operating System :: OS Independent
Requires-Python: >=3.6
License-File: LICENSE
Requires-Dist: requests
Requires-Dist: click
Requires-Dist: markdown
Requires-Dist: opencv-python
